{
  "code": "GSTGMIC",
  "price_gbn": "tiered_price",
  "rows": [
    {
      "ORD_CNT": 1,
      "PRICE": 6000,
      "ORG_PRICE": 6000,
      "unit": 6000,
      "discPct": 0
    },
    {
      "ORD_CNT": 2,
      "PRICE": 12000,
      "ORG_PRICE": 12000,
      "unit": 6000,
      "discPct": 0
    },
    {
      "ORD_CNT": 5,
      "PRICE": 30000,
      "ORG_PRICE": 30000,
      "unit": 6000,
      "discPct": 0
    },
    {
      "ORD_CNT": 10,
      "PRICE": 60000,
      "ORG_PRICE": 60000,
      "unit": 6000,
      "discPct": 0
    },
    {
      "ORD_CNT": 30,
      "PRICE": 180000,
      "ORG_PRICE": 180000,
      "unit": 6000,
      "discPct": 0
    },
    {
      "ORD_CNT": 50,
      "PRICE": 300000,
      "ORG_PRICE": 300000,
      "unit": 6000,
      "discPct": 0
    },
    {
      "ORD_CNT": 100,
      "PRICE": 600000,
      "ORG_PRICE": 600000,
      "unit": 6000,
      "discPct": 0
    },
    {
      "ORD_CNT": 300,
      "PRICE": 1800000,
      "ORG_PRICE": 1800000,
      "unit": 6000,
      "discPct": 0
    },
    {
      "ORD_CNT": 1000,
      "PRICE": 6000000,
      "ORG_PRICE": 6000000,
      "unit": 6000,
      "discPct": 0
    }
  ],
  "flatUnit": true,
  "anyDisc": false,
  "capturedAt": "2026-06-02T22:46:00.908Z"
}